Metadata-Version: 2.1
Name: face-detectors
Version: 0.1.0
Summary: Light weight face detector hight level client with multiple detection techniques.
Home-page: https://github.com/Saadmairaj/face-detectors
Author: Saad Mairaj
Author-email: Saadmairaj@yahoo.in
License: Apache
Project-URL: Bug Reports, https://github.com/Saadmairaj/face-detectors/issues
Project-URL: Source, https://github.com/Saadmairaj/face-detectors
Project-URL: Documentation, https://github.com/Saadmairaj/face-detectors#documentation
Keywords: machine learning,face,detector,face detection,CNN,dlib,ultrafast,HOG,caffemodel
Platform: UNKNOWN
Classifier: Environment :: MacOS X
Classifier: Environment :: Win32 (MS Windows)
Classifier: Environment :: X11 Applications
Classifier: Intended Audience :: Developers
Classifier: Intended Audience :: Education
Classifier: Intended Audience :: End Users/Desktop
Classifier: Operating System :: OS Independent
Classifier: Programming Language :: Python :: 3 :: Only
Classifier: Topic :: Software Development
Classifier: Topic :: Software Development :: Build Tools
Classifier: Topic :: Software Development :: Libraries :: Python Modules
Classifier: Topic :: Software Development :: Widget Sets
Classifier: License :: OSI Approved :: Apache Software License
Requires-Python: >=3.6
License-File: LICENSE
